LICENSE
MANIFEST.in
README.md
setup.cfg
setup.py
trivup/__init__.py
trivup/trivup.py
trivup.egg-info/PKG-INFO
trivup.egg-info/SOURCES.txt
trivup.egg-info/dependency_links.txt
trivup.egg-info/requires.txt
trivup.egg-info/top_level.txt
trivup/apps/KafkaBrokerApp.py
trivup/apps/KerberosKdcApp.py
trivup/apps/OauthbearerOIDCApp.py
trivup/apps/SchemaRegistryApp.py
trivup/apps/SslApp.py
trivup/apps/ZookeeperApp.py
trivup/apps/__init__.py
trivup/apps/KafkaBrokerApp/deploy.sh
trivup/apps/KafkaBrokerApp/log4j.properties.template
trivup/apps/KafkaBrokerApp/server.properties.template
trivup/apps/KerberosKdcApp/kdc.conf.template
trivup/apps/KerberosKdcApp/krb5.conf.template
trivup/apps/ZookeeperApp/zookeeper.properties.template
trivup/clusters/KafkaCluster.py
trivup/clusters/__init__.py