Metadata-Version: 1.1
Name: trivup
Version: 0.12.0
Summary: Trivially Up a cluster of programs, such as a Kafka cluster
Home-page: https://github.com/edenhill/trivup
Author: Magnus Edenhill
Author-email: magnus@edenhill.se
License: UNKNOWN
Platform: UNKNOWN
Classifier: Programming Language :: Python :: 3
Classifier: Programming Language :: Python :: 2
Classifier: License :: OSI Approved :: BSD License
Classifier: Operating System :: OS Independent
